form_to_excel
