Metadata-Version: 1.0
Name: form-to-excel
Version: 0.1.2
Summary: Convert Word/PDF documents to Excel Workbooks
Home-page: https://github.com/aseli1/dm_form_to_excel
Author: Anthony Seliga
Author-email: anthony.seliga@gmail.com
License: MIT
Platform: UNKNOWN
